{
  "@context": "http://iiif.io/api/presentation/2/context.json",
  "@id": "https://nicolearaya.github.io/mit-tarot/list-TD0133-01-07.json",
  "@type": "sc:AnnotationList",
  "resources": [
    {
      "@type": "oa:Annotation",
      "motivation": "oa:tagging",
      "resource":{
        "@id": "https://nicolearaya.github.io/mit-tarot/list-TD0133-01-07-000.json",
        "@type": "dctypes:Text",
        "format": "text/plain",
        "chars": "person, 75.7% confidence (Google Vision)"
      },
      "on": "http://libme25-0479439.mit.edu/objects/tarot/TD0133-01-07#xywh=1152,945,177,819"
    }
  ]
}